{
  "treeShake": {
    "lodash-es": {
      "uniq": false,
      "curry": false,
      "now": false,
      "filter": false,
      "isObjectLike": false,
      "times": false,
      "isFinite": false,
      "toArray": false,
      "repeat": false,
      "divide": false,
      "zipWith": false,
      "keyBy": false,
      "lowerCase": false,
      "unionWith": false,
      "delay": true,
      "trim": false,
      "fill": false,
      "overSome": false,
      "pullAllBy": false,
      "gte": false,
      "flip": false,
      "nth": false,
      "wrapperAt": false,
      "assignInWith": false,
      "functionsIn": false,
      "nthArg": false,
      "sumBy": false,
      "takeRightWhile": false,
      "lte": false,
      "flowRight": false,
      "isSafeInteger": false,
      "parseInt": false,
      "bindKey": false,
      "forIn": false,
      "groupBy": false,
      "maxBy": false,
      "matches": false,
      "padStart": false,
      "wrapperReverse": false,
      "isMap": false,
      "cond": false,
      "overArgs": false,
      "defaultsDeep": false,
      "toInteger": false,
      "truncate": false,
      "invertBy": false,
      "differenceBy": false,
      "after": false,
      "intersection": false,
      "intersectionBy": false,
      "bind": false,
      "countBy": false,
      "lodash": false,
      "mapValues": false,
      "negate": false,
      "orderBy": false,
      "pullAt": false,
      "sortedUniqBy": false,
      "omitBy": false,
      "xor": false,
      "concat": false,
      "isArguments": false,
      "matchesProperty": false,
      "sum": false,
      "toPairs": false,
      "trimStart": false,
      "unset": false,
      "update": false,
      "wrapperCommit": false,
      "extend": false,
      "find": false,
      "invokeMap": false,
      "assign": false,
      "reduce": false,
      "isError": false,
      "constant": false,
      "at": false,
      "floor": false,
      "chunk": false,
      "reject": false,
      "isEmpty": false,
      "sortedIndexOf": false,
      "value": false,
      "uniqWith": false,
      "zip": false,
      "flatten": false,
      "flatMapDepth": false,
      "isUndefined": false,
      "initial": false,
      "startCase": false,
      "toPairsIn": false,
      "toPlainObject": false,
      "escape": false,
      "has": false,
      "omit": false,
      "first": false,
      "merge": false,
      "findLastKey": false,
      "stubTrue": false,
      "spread": false,
      "wrapperValue": false,
      "ary": false,
      "get": false,
      "valueOf": false,
      "some": false,
      "wrapperChain": false,
      "tail": false,
      "lt": false,
      "overEvery": false,
      "zipObjectDeep": false,
      "upperFirst": false,
      "sample": false,
      "result": false,
      "last": false,
      "compact": false,
      "shuffle": false,
      "isNaN": false,
      "conforms": false,
      "reduceRight": false,
      "isEqualWith": false,
      "throttle": false,
      "slice": false,
      "toPath": false,
      "clone": false,
      "isElement": false,
      "flatMapDeep": false,
      "extendWith": false,
      "method": false,
      "sortedIndexBy": false,
      "isFunction": false,
      "stubString": false,
      "mapKeys": false,
      "isBoolean": false,
      "multiply": false,
      "lowerFirst": false,
      "sortedUniq": false,
      "toUpper": false,
      "forOwn": false,
      "plant": false,
      "transform": false,
      "wrapperNext": false,
      "stubFalse": false,
      "xorBy": false,
      "forEachRight": false,
      "isMatch": false,
      "min": false,
      "forInRight": false,
      "remove": false,
      "clamp": false,
      "isInteger": false,
      "thru": false,
      "identity": false,
      "memoize": false,
      "zipObject": false,
      "reverse": false,
      "partialRight": false,
      "pullAllWith": false,
      "add": false,
      "lastIndexOf": false,
      "isPlainObject": false,
      "range": false,
      "pick": false,
      "chain": false,
      "entriesIn": false,
      "isEqual": false,
      "isNative": false,
      "toLength": false,
      "uniqBy": false,
      "isNumber": false,
      "debounce": false,
      "meanBy": false,
      "isWeakMap": false,
      "capitalize": false,
      "dropRight": false,
      "padEnd": false,
      "intersectionWith": false,
      "template": false,
      "entries": false,
      "isBuffer": false,
      "defaultTo": false,
      "union": false,
      "property": false,
      "uniqueId": false,
      "valuesIn": false,
      "defaults": false,
      "pickBy": false,
      "isString": false,
      "findIndex": false,
      "sortedLastIndexOf": false,
      "findLast": false,
      "isSet": false,
      "mergeWith": false,
      "ceil": false,
      "pad": false,
      "isDate": false,
      "methodOf": false,
      "sortedIndex": false,
      "gt": false,
      "commit": false,
      "castArray": false,
      "next": false,
      "partition": false,
      "keys": false,
      "escapeRegExp": false,
      "isSymbol": false,
      "mean": false,
      "split": false,
      "dropWhile": false,
      "defer": false,
      "deburr": false,
      "toIterator": false,
      "round": false,
      "flow": false,
      "assignWith": false,
      "assignIn": false,
      "conformsTo": false,
      "every": false,
      "flattenDepth": false,
      "forEach": false,
      "startsWith": false,
      "templateSettings": false,
      "takeRight": false,
      "values": false,
      "toLower": false,
      "unzip": false,
      "unzipWith": false,
      "toFinite": false,
      "indexOf": false,
      "random": true,
      "before": false,
      "toSafeInteger": false,
      "isNull": false,
      "pull": false,
      "wrapperLodash": false,
      "isMatchWith": false,
      "trimEnd": false,
      "flattenDeep": false,
      "unary": false,
      "attempt": false,
      "isRegExp": false,
      "upperCase": false,
      "camelCase": false,
      "rest": false,
      "curryRight": false,
      "flatMap": false,
      "cloneDeepWith": false,
      "isArrayLikeObject": false,
      "wrapperToIterator": false,
      "endsWith": false,
      "difference": false,
      "includes": false,
      "replace": false,
      "each": false,
      "words": false,
      "isNil": false,
      "sortedLastIndex": false,
      "pullAll": false,
      "dropRightWhile": false,
      "cloneWith": false,
      "map": false,
      "sortBy": true,
      "differenceWith": false,
      "propertyOf": false,
      "minBy": false,
      "without": false,
      "isLength": false,
      "rearg": false,
      "drop": false,
      "sortedLastIndexBy": false,
      "cloneDeep": false,
      "join": false,
      "size": false,
      "updateWith": false,
      "partial": false,
      "isArrayLike": false,
      "toNumber": false,
      "toString": false,
      "unescape": false,
      "wrapperPlant": false,
      "hasIn": false,
      "invert": false,
      "invoke": false,
      "wrap": false,
      "once": false,
      "subtract": false,
      "sampleSize": false,
      "head": false,
      "stubArray": false,
      "findKey": false,
      "iteratee": false,
      "toJSON": false,
      "xorWith": false,
      "mixin": false,
      "rangeRight": false,
      "snakeCase": false,
      "kebabCase": false,
      "findLastIndex": false,
      "isTypedArray": false,
      "takeWhile": false,
      "eachRight": false,
      "over": false,
      "isArray": false,
      "unionBy": false,
      "forOwnRight": false,
      "create": false,
      "default": true,
      "isObject": false,
      "take": false,
      "set": false,
      "keysIn": false,
      "noop": false,
      "setWith": false,
      "bindAll": false,
      "eq": false,
      "tap": false,
      "inRange": false,
      "max": false,
      "isArrayBuffer": false,
      "stubObject": false,
      "isWeakSet": false,
      "fromPairs": false,
      "functions": false,
      "chunk_characteristics": {
        "entry_module_id": "../../../node_modules/.pnpm/lodash-es@4.17.21/node_modules/lodash-es/lodash.js",
        "is_runtime_chunk": false,
        "has_runtime": false,
        "is_entrypoint": false,
        "can_be_initial": false,
        "is_only_initial": false,
        "chunk_format": "jsonp",
        "chunk_loading_type": null,
        "runtime_names": [
          "main"
        ],
        "entry_name": null,
        "has_async_chunks": false,
        "chunk_files": [
          "node_modules_pnpm_lodash-es_4_17_21_node_modules_lodash-es_lodash_js.js"
        ],
        "is_shared_chunk": false,
        "shared_modules": []
      }
    },
    "react-router-dom": {
      "useLoaderData": false,
      "useNavigate": true,
      "useParams": false,
      "useInRouterContext": false,
      "UNSAFE_useFogOFWarDiscovery": false,
      "UNSAFE_FetchersContext": false,
      "Form": false,
      "Scripts": false,
      "UNSAFE_DataRouterContext": false,
      "RouterProvider": false,
      "createMemorySessionStorage": false,
      "createStaticHandler": false,
      "UNSAFE_WithComponentProps": false,
      "unstable_RSCHydratedRouter": false,
      "unstable_usePrompt": false,
      "Meta": false,
      "UNSAFE_ViewTransitionContext": false,
      "UNSAFE_getPatchRoutesOnNavigationFunction": false,
      "createRequestHandler": false,
      "createCookieSessionStorage": false,
      "createRoutesFromElements": false,
      "href": false,
      "createBrowserRouter": false,
      "parsePath": false,
      "createHashRouter": false,
      "isRouteErrorResponse": false,
      "generatePath": false,
      "useViewTransitionState": false,
      "IDLE_BLOCKER": false,
      "useMatch": false,
      "Routes": true,
      "ScrollRestoration": false,
      "NavigationType": false,
      "UNSAFE_WithErrorBoundaryProps": false,
      "unstable_routeRSCServerRequest": false,
      "useBlocker": false,
      "UNSAFE_ErrorResponseImpl": false,
      "IDLE_FETCHER": false,
      "UNSAFE_RemixErrorBoundary": false,
      "UNSAFE_mapRouteProperties": false,
      "useOutletContext": false,
      "UNSAFE_RSCDefaultRootErrorBoundary": false,
      "UNSAFE_getTurboStreamSingleFetchDataStrategy": false,
      "StaticRouter": false,
      "UNSAFE_NavigationContext": false,
      "UNSAFE_withHydrateFallbackProps": false,
      "createMemoryRouter": false,
      "createStaticRouter": false,
      "isCookie": false,
      "redirectDocument": false,
      "useActionData": false,
      "UNSAFE_createClientRoutes": false,
      "BrowserRouter": true,
      "createCookie": false,
      "useAsyncValue": false,
      "UNSAFE_hydrationRouteProperties": false,
      "useFetchers": false,
      "StaticRouterProvider": false,
      "UNSAFE_createClientRoutesWithHMRRevalidationOptOut": false,
      "createSessionStorage": false,
      "isSession": false,
      "Link": false,
      "unstable_createContext": false,
      "UNSAFE_ServerMode": false,
      "useRoutes": false,
      "UNSAFE_deserializeErrors": false,
      "UNSAFE_withErrorBoundaryProps": false,
      "useMatches": false,
      "useLocation": true,
      "useBeforeUnload": false,
      "unstable_RSCStaticRouter": false,
      "UNSAFE_RouteContext": false,
      "createPath": false,
      "createSession": false,
      "useRouteError": false,
      "Links": false,
      "UNSAFE_SingleFetchRedirectSymbol": false,
      "UNSAFE_DataRouterStateContext": false,
      "UNSAFE_createRouter": false,
      "createRoutesStub": false,
      "unstable_createCallServer": false,
      "resolvePath": false,
      "data": false,
      "matchPath": false,
      "useFormAction": false,
      "HashRouter": false,
      "UNSAFE_invariant": false,
      "Navigate": true,
      "UNSAFE_getHydrationData": false,
      "createSearchParams": false,
      "UNSAFE_useScrollRestoration": false,
      "IDLE_NAVIGATION": false,
      "Route": true,
      "Await": false,
      "createRoutesFromChildren": false,
      "useFetcher": false,
      "unstable_getRSCStream": false,
      "Router": false,
      "useRouteLoaderData": false,
      "useRevalidator": false,
      "UNSAFE_FrameworkContext": false,
      "useResolvedPath": false,
      "UNSAFE_withComponentProps": false,
      "UNSAFE_WithHydrateFallbackProps": false,
      "NavLink": false,
      "UNSAFE_LocationContext": false,
      "UNSAFE_shouldHydrateRouteLoader": false,
      "useHref": false,
      "useLinkClickHandler": false,
      "unstable_setDevServerHooks": false,
      "redirect": false,
      "UNSAFE_createBrowserHistory": false,
      "HydratedRouter": false,
      "matchRoutes": false,
      "useSearchParams": false,
      "MemoryRouter": false,
      "Outlet": false,
      "ServerRouter": false,
      "unstable_HistoryRouter": false,
      "PrefetchPageLinks": false,
      "unstable_RouterContextProvider": false,
      "useAsyncError": false,
      "UNSAFE_decodeViaTurboStream": false,
      "renderMatches": false,
      "replace": false,
      "useNavigation": false,
      "useSubmit": false,
      "useNavigationType": false,
      "useOutlet": false,
      "chunk_characteristics": {
        "entry_module_id": "../../../node_modules/.pnpm/react-router-dom@7.8.0_react-dom@18.3.1_react@18.3.1/node_modules/react-router-dom/dist/index.mjs",
        "is_runtime_chunk": false,
        "has_runtime": false,
        "is_entrypoint": false,
        "can_be_initial": false,
        "is_only_initial": false,
        "chunk_format": "jsonp",
        "chunk_loading_type": null,
        "runtime_names": [
          "main"
        ],
        "entry_name": null,
        "has_async_chunks": false,
        "chunk_files": [
          "node_modules_pnpm_react-router-dom_7_8_0_react-dom_18_3_1_react_18_3_1_node_modules_react-rou-efed210.js"
        ],
        "is_shared_chunk": false,
        "shared_modules": []
      }
    },
    "react-chartjs-2": {
      "Scatter": false,
      "Bubble": false,
      "Radar": false,
      "Pie": false,
      "Bar": false,
      "getElementAtEvent": false,
      "getElementsAtEvent": false,
      "PolarArea": false,
      "Doughnut": true,
      "Line": true,
      "Chart": false,
      "getDatasetAtEvent": false,
      "chunk_characteristics": {
        "entry_module_id": "../../../node_modules/.pnpm/react-chartjs-2@5.3.0_chart.js@4.5.0_react@18.3.1/node_modules/react-chartjs-2/dist/index.js",
        "is_runtime_chunk": false,
        "has_runtime": false,
        "is_entrypoint": false,
        "can_be_initial": false,
        "is_only_initial": false,
        "chunk_format": "jsonp",
        "chunk_loading_type": null,
        "runtime_names": [
          "main"
        ],
        "entry_name": null,
        "has_async_chunks": true,
        "chunk_files": [
          "node_modules_pnpm_react-chartjs-2_5_3_0_chart_js_4_5_0_react_18_3_1_node_modules_react-chartj-c8072e1.js"
        ],
        "is_shared_chunk": true,
        "shared_modules": [
          "react",
          "chart.js"
        ]
      }
    },
    "react": {
      "chunk_characteristics": {
        "entry_module_id": "../../../node_modules/.pnpm/react@18.3.1/node_modules/react/index.js",
        "is_runtime_chunk": false,
        "has_runtime": false,
        "is_entrypoint": false,
        "can_be_initial": false,
        "is_only_initial": false,
        "chunk_format": "jsonp",
        "chunk_loading_type": null,
        "runtime_names": [
          "main"
        ],
        "entry_name": null,
        "has_async_chunks": false,
        "chunk_files": [
          "node_modules_pnpm_react_18_3_1_node_modules_react_index_js.js"
        ],
        "is_shared_chunk": false,
        "shared_modules": []
      }
    },
    "@reduxjs/toolkit": {
      "createSelectorCreator": false,
      "applyMiddleware": false,
      "asyncThunkCreator": false,
      "bindActionCreators": false,
      "buildCreateSlice": false,
      "createDynamicMiddleware": false,
      "createImmutableStateInvariantMiddleware": false,
      "__DO_NOT_USE__ActionTypes": false,
      "createSerializableStateInvariantMiddleware": false,
      "createDraftSafeSelectorCreator": false,
      "formatProdErrorMessage": false,
      "TaskAbortError": false,
      "freeze": false,
      "createReducer": false,
      "clearAllListeners": false,
      "createStore": false,
      "addListener": false,
      "miniSerializeError": false,
      "combineSlices": false,
      "createSlice": true,
      "isRejectedWithValue": false,
      "isPlainObject": false,
      "SHOULD_AUTOBATCH": false,
      "configureStore": true,
      "isPlain": false,
      "autoBatchEnhancer": false,
      "isImmutableDefault": false,
      "Tuple": false,
      "isAsyncThunkAction": false,
      "createAction": false,
      "ReducerType": false,
      "isAnyOf": false,
      "isFulfilled": false,
      "createDraftSafeSelector": false,
      "findNonSerializableValue": false,
      "weakMapMemoize": false,
      "isActionCreator": false,
      "createListenerMiddleware": false,
      "current": false,
      "combineReducers": false,
      "isFluxStandardAction": false,
      "legacy_createStore": false,
      "createEntityAdapter": false,
      "compose": false,
      "createNextState": false,
      "isRejected": false,
      "lruMemoize": false,
      "original": false,
      "isAllOf": false,
      "createAsyncThunk": true,
      "isAction": false,
      "prepareAutoBatched": false,
      "createSelector": false,
      "isDraft": false,
      "createActionCreatorInvariantMiddleware": false,
      "removeListener": false,
      "unwrapResult": false,
      "isPending": false,
      "nanoid": false,
      "chunk_characteristics": {
        "entry_module_id": "../../../node_modules/.pnpm/@reduxjs+toolkit@2.8.2_react-redux@9.2.0_react@18.3.1/node_modules/@reduxjs/toolkit/dist/redux-toolkit.modern.mjs",
        "is_runtime_chunk": false,
        "has_runtime": false,
        "is_entrypoint": false,
        "can_be_initial": false,
        "is_only_initial": false,
        "chunk_format": "jsonp",
        "chunk_loading_type": null,
        "runtime_names": [
          "main"
        ],
        "entry_name": null,
        "has_async_chunks": false,
        "chunk_files": [
          "node_modules_pnpm_reduxjs_toolkit_2_8_2_react-redux_9_2_0_react_18_3_1_node_modules_reduxjs_t-505f80.js"
        ],
        "is_shared_chunk": false,
        "shared_modules": []
      }
    },
    "@ant-design/icons": {
      "GlobalOutlined": false,
      "DotChartOutlined": false,
      "DoubleLeftOutlined": false,
      "JavaOutlined": false,
      "HomeTwoTone": false,
      "EyeInvisibleTwoTone": false,
      "RedditOutlined": false,
      "UnorderedListOutlined": false,
      "AppstoreFilled": false,
      "ZoomInOutlined": false,
      "FolderFilled": false,
      "FolderAddFilled": false,
      "MacCommandOutlined": false,
      "EditFilled": false,
      "FilePdfOutlined": false,
      "AndroidFilled": false,
      "PicLeftOutlined": false,
      "LinkedinFilled": false,
      "TransactionOutlined": false,
      "PoundCircleTwoTone": false,
      "SendOutlined": false,
      "Html5Filled": false,
      "LeftCircleOutlined": false,
      "PicRightOutlined": false,
      "PlayCircleFilled": false,
      "ScheduleFilled": false,
      "TaobaoSquareFilled": false,
      "TagsFilled": false,
      "FieldNumberOutlined": false,
      "PieChartTwoTone": false,
      "ShoppingCartOutlined": false,
      "WarningOutlined": false,
      "CompassOutlined": false,
      "WeiboSquareOutlined": false,
      "CodepenOutlined": false,
      "CompassFilled": false,
      "CrownTwoTone": false,
      "ExperimentTwoTone": false,
      "FileExcelFilled": false,
      "CopyrightOutlined": false,
      "HarmonyOSOutlined": false,
      "BankOutlined": false,
      "BorderHorizontalOutlined": false,
      "CopyrightCircleFilled": false,
      "CloudSyncOutlined": false,
      "CreditCardFilled": false,
      "FireOutlined": false,
      "DiscordFilled": false,
      "FrownTwoTone": false,
      "GitlabFilled": false,
      "ScheduleTwoTone": false,
      "SolutionOutlined": false,
      "InsuranceTwoTone": false,
      "FileExclamationOutlined": false,
      "SwapRightOutlined": false,
      "setTwoToneColor": false,
      "SketchCircleFilled": false,
      "FileZipOutlined": false,
      "ReconciliationOutlined": false,
      "CodeSandboxSquareFilled": false,
      "AppstoreTwoTone": false,
      "DeleteFilled": false,
      "ChromeFilled": false,
      "ColumnWidthOutlined": false,
      "DribbbleCircleFilled": false,
      "DoubleRightOutlined": false,
      "FrownFilled": false,
      "InfoCircleTwoTone": false,
      "QuestionCircleFilled": false,
      "RightCircleOutlined": false,
      "InsertRowAboveOutlined": false,
      "ThunderboltTwoTone": false,
      "AccountBookFilled": false,
      "WechatWorkFilled": false,
      "WifiOutlined": false,
      "HeartFilled": false,
      "RedditSquareFilled": false,
      "ApiOutlined": false,
      "AlipayCircleOutlined": false,
      "TableOutlined": true,
      "PieChartOutlined": false,
      "RadiusBottomleftOutlined": false,
      "FlagTwoTone": false,
      "default": true,
      "DislikeFilled": false,
      "ContainerOutlined": false,
      "AppleFilled": false,
      "BoldOutlined": false,
      "ReadOutlined": false,
      "RubyOutlined": false,
      "AmazonOutlined": false,
      "FileTextTwoTone": false,
      "HeartOutlined": false,
      "CalculatorOutlined": false,
      "CaretUpOutlined": false,
      "AimOutlined": false,
      "DollarCircleOutlined": false,
      "AlertOutlined": false,
      "FileImageFilled": false,
      "IeSquareFilled": false,
      "PlusSquareTwoTone": false,
      "RollbackOutlined": false,
      "CloudUploadOutlined": false,
      "InteractionOutlined": false,
      "FileImageTwoTone": false,
      "RadiusUpleftOutlined": false,
      "FileWordFilled": false,
      "NotificationTwoTone": false,
      "RightCircleFilled": false,
      "SnippetsFilled": false,
      "ClusterOutlined": false,
      "PrinterOutlined": false,
      "XFilled": false,
      "DownloadOutlined": false,
      "SaveOutlined": true,
      "DisconnectOutlined": false,
      "DollarCircleFilled": false,
      "PayCircleFilled": false,
      "BankTwoTone": false,
      "BilibiliFilled": false,
      "SwapOutlined": false,
      "DiscordOutlined": false,
      "LayoutOutlined": false,
      "FileUnknownFilled": false,
      "CaretRightFilled": false,
      "FilterFilled": false,
      "FacebookFilled": false,
      "HeatMapOutlined": false,
      "MessageOutlined": false,
      "TaobaoCircleOutlined": false,
      "YahooFilled": false,
      "DeploymentUnitOutlined": false,
      "ExperimentFilled": false,
      "FileSearchOutlined": false,
      "CompressOutlined": false,
      "IdcardTwoTone": false,
      "MehFilled": false,
      "UpSquareFilled": false,
      "UserOutlined": true,
      "HddFilled": false,
      "DribbbleSquareOutlined": false,
      "SignatureOutlined": false,
      "PictureTwoTone": false,
      "CheckCircleFilled": false,
      "CalendarFilled": false,
      "MediumOutlined": false,
      "SecurityScanTwoTone": false,
      "SwapLeftOutlined": false,
      "GiftOutlined": false,
      "GooglePlusCircleFilled": false,
      "PropertySafetyFilled": false,
      "LockOutlined": false,
      "EuroCircleFilled": false,
      "YahooOutlined": false,
      "LoginOutlined": false,
      "LeftSquareTwoTone": false,
      "PhoneFilled": false,
      "FilePptTwoTone": false,
      "CompassTwoTone": false,
      "TwitchOutlined": false,
      "CameraTwoTone": false,
      "DashboardFilled": false,
      "StarTwoTone": false,
      "FilterOutlined": false,
      "DotNetOutlined": false,
      "BugOutlined": false,
      "EnterOutlined": false,
      "RedEnvelopeTwoTone": false,
      "ManOutlined": false,
      "FastForwardFilled": false,
      "FolderOpenOutlined": false,
      "MobileFilled": false,
      "FileWordOutlined": false,
      "FolderOpenFilled": false,
      "ForwardOutlined": false,
      "FileJpgOutlined": false,
      "TeamOutlined": false,
      "ArrowDownOutlined": true,
      "GoldOutlined": false,
      "InsertRowRightOutlined": false,
      "ClockCircleOutlined": false,
      "MinusCircleOutlined": false,
      "FileTextFilled": false,
      "SelectOutlined": false,
      "BulbFilled": false,
      "ContactsOutlined": false,
      "ControlOutlined": false,
      "DingtalkCircleFilled": false,
      "LeftOutlined": false,
      "LeftSquareFilled": false,
      "PinterestFilled": false,
      "AudioFilled": false,
      "FileSyncOutlined": false,
      "AmazonCircleFilled": false,
      "HourglassTwoTone": false,
      "AreaChartOutlined": false,
      "CodeSandboxOutlined": false,
      "FilePptOutlined": false,
      "DownCircleTwoTone": false,
      "PrinterFilled": false,
      "FolderAddOutlined": false,
      "FileExclamationFilled": false,
      "PushpinFilled": false,
      "LeftCircleTwoTone": false,
      "QqOutlined": false,
      "SmileOutlined": false,
      "SmileTwoTone": false,
      "NodeCollapseOutlined": false,
      "SoundTwoTone": false,
      "CameraFilled": false,
      "BorderLeftOutlined": false,
      "DeleteTwoTone": false,
      "AliyunOutlined": false,
      "AudioOutlined": false,
      "FastBackwardFilled": false,
      "QqCircleFilled": false,
      "RiseOutlined": false,
      "SketchOutlined": false,
      "SkinTwoTone": false,
      "BackwardFilled": false,
      "CheckSquareTwoTone": false,
      "UserDeleteOutlined": false,
      "ApiTwoTone": false,
      "TruckOutlined": false,
      "SlackOutlined": false,
      "MinusOutlined": false,
      "DockerOutlined": false,
      "StarOutlined": false,
      "SafetyCertificateFilled": false,
      "SoundFilled": false,
      "MinusSquareTwoTone": false,
      "DesktopOutlined": false,
      "IssuesCloseOutlined": false,
      "StopTwoTone": false,
      "ToTopOutlined": false,
      "CrownFilled": false,
      "UpCircleFilled": false,
      "FolderAddTwoTone": false,
      "MonitorOutlined": false,
      "WalletTwoTone": false,
      "LockTwoTone": false,
      "MutedOutlined": false,
      "TrademarkCircleTwoTone": false,
      "ZhihuOutlined": false,
      "ZoomOutOutlined": false,
      "AliwangwangFilled": false,
      "CloseOutlined": false,
      "EnvironmentFilled": false,
      "MobileTwoTone": false,
      "BorderTopOutlined": false,
      "BorderRightOutlined": false,
      "PictureOutlined": false,
      "ExclamationOutlined": false,
      "SortAscendingOutlined": false,
      "TrophyOutlined": false,
      "CopyrightCircleTwoTone": false,
      "CiTwoTone": false,
      "InsuranceFilled": false,
      "AudioMutedOutlined": false,
      "ItalicOutlined": false,
      "ReloadOutlined": true,
      "ExclamationCircleFilled": false,
      "QuestionCircleOutlined": false,
      "RocketOutlined": false,
      "LogoutOutlined": true,
      "SafetyCertificateOutlined": false,
      "ShrinkOutlined": false,
      "NotificationOutlined": false,
      "LinkOutlined": false,
      "CloseCircleOutlined": false,
      "CarryOutTwoTone": false,
      "CloseSquareFilled": false,
      "FontSizeOutlined": false,
      "RetweetOutlined": false,
      "CustomerServiceFilled": false,
      "BankFilled": false,
      "SignatureFilled": false,
      "SettingOutlined": true,
      "EditOutlined": true,
      "AlignLeftOutlined": false,
      "RightSquareTwoTone": false,
      "BuildOutlined": false,
      "FileZipFilled": false,
      "GoogleCircleFilled": false,
      "HddOutlined": false,
      "NumberOutlined": false,
      "RocketTwoTone": false,
      "WindowsOutlined": false,
      "CaretUpFilled": false,
      "DeleteColumnOutlined": false,
      "SkypeOutlined": false,
      "MenuFoldOutlined": false,
      "BehanceSquareOutlined": false,
      "StepForwardOutlined": false,
      "ControlTwoTone": false,
      "PhoneOutlined": false,
      "EuroTwoTone": false,
      "SkinOutlined": false,
      "DownCircleFilled": false,
      "FileAddFilled": false,
      "BackwardOutlined": false,
      "CalendarTwoTone": false,
      "DownSquareFilled": false,
      "FieldBinaryOutlined": false,
      "FormatPainterFilled": false,
      "ClockCircleFilled": false,
      "DropboxCircleFilled": false,
      "GroupOutlined": false,
      "LikeOutlined": false,
      "MessageFilled": false,
      "QuestionCircleTwoTone": false,
      "ReconciliationFilled": false,
      "FileProtectOutlined": false,
      "SaveFilled": false,
      "FileZipTwoTone": false,
      "IconProvider": false,
      "ShakeOutlined": false,
      "UpCircleOutlined": false,
      "UsbOutlined": false,
      "FileMarkdownOutlined": false,
      "GooglePlusOutlined": false,
      "FileTwoTone": false,
      "FastForwardOutlined": false,
      "QrcodeOutlined": false,
      "SkinFilled": false,
      "DingtalkOutlined": false,
      "UploadOutlined": false,
      "TrophyFilled": false,
      "FileExclamationTwoTone": false,
      "TrophyTwoTone": false,
      "WhatsAppOutlined": false,
      "DingtalkSquareFilled": false,
      "FormatPainterOutlined": false,
      "GoldFilled": false,
      "ProjectOutlined": false,
      "WechatFilled": false,
      "ThunderboltOutlined": false,
      "ShopTwoTone": false,
      "FileExcelTwoTone": false,
      "SkypeFilled": false,
      "CopyrightCircleOutlined": false,
      "PartitionOutlined": false,
      "HourglassOutlined": false,
      "ForkOutlined": false,
      "InteractionFilled": false,
      "BgColorsOutlined": false,
      "GatewayOutlined": false,
      "PlusCircleFilled": false,
      "ContainerTwoTone": false,
      "SaveTwoTone": false,
      "InsertRowLeftOutlined": false,
      "SnippetsOutlined": false,
      "InteractionTwoTone": false,
      "WarningTwoTone": false,
      "MenuUnfoldOutlined": false,
      "AppleOutlined": false,
      "FlagFilled": false,
      "CiCircleTwoTone": false,
      "CodepenSquareFilled": false,
      "CopyFilled": false,
      "DingdingOutlined": false,
      "PauseOutlined": false,
      "SoundOutlined": false,
      "DiffFilled": false,
      "FolderViewOutlined": false,
      "ClockCircleTwoTone": false,
      "FacebookOutlined": false,
      "RadiusSettingOutlined": false,
      "MessageTwoTone": false,
      "SettingTwoTone": false,
      "SignalFilled": false,
      "TrademarkCircleFilled": false,
      "TabletTwoTone": false,
      "DatabaseFilled": false,
      "EnvironmentTwoTone": false,
      "PaperClipOutlined": false,
      "UnlockTwoTone": false,
      "MediumWorkmarkOutlined": false,
      "PlusSquareFilled": false,
      "UngroupOutlined": false,
      "GifOutlined": false,
      "ColumnHeightOutlined": false,
      "CustomerServiceOutlined": false,
      "FileGifOutlined": false,
      "FunnelPlotFilled": false,
      "LikeFilled": false,
      "MediumCircleFilled": false,
      "MergeOutlined": false,
      "MobileOutlined": false,
      "MoneyCollectFilled": false,
      "MoneyCollectOutlined": false,
      "PropertySafetyTwoTone": false,
      "RocketFilled": false,
      "DiffOutlined": false,
      "ScissorOutlined": false,
      "CopyrightTwoTone": false,
      "ShopOutlined": false,
      "DollarCircleTwoTone": false,
      "FolderTwoTone": false,
      "CheckOutlined": false,
      "MehOutlined": false,
      "SlackSquareFilled": false,
      "SlackSquareOutlined": false,
      "StepForwardFilled": false,
      "VerifiedOutlined": false,
      "UndoOutlined": false,
      "RestTwoTone": false,
      "TagsTwoTone": false,
      "ForwardFilled": false,
      "TagTwoTone": false,
      "FastBackwardOutlined": false,
      "PauseCircleFilled": false,
      "ProfileOutlined": false,
      "ToolFilled": false,
      "VideoCameraAddOutlined": false,
      "YuqueFilled": false,
      "IeOutlined": false,
      "ChromeOutlined": false,
      "DeliveredProcedureOutlined": false,
      "FileExcelOutlined": false,
      "ThunderboltFilled": false,
      "CodeOutlined": false,
      "SunOutlined": false,
      "FilePptFilled": false,
      "LineHeightOutlined": false,
      "OrderedListOutlined": false,
      "PushpinTwoTone": false,
      "AlignCenterOutlined": false,
      "RotateLeftOutlined": false,
      "TrademarkOutlined": false,
      "UnlockFilled": false,
      "UnlockOutlined": false,
      "BarcodeOutlined": false,
      "EyeFilled": false,
      "SpotifyFilled": false,
      "UpSquareTwoTone": false,
      "DislikeOutlined": false,
      "CodepenCircleFilled": false,
      "LoadingOutlined": false,
      "HourglassFilled": false,
      "MacCommandFilled": false,
      "PlayCircleTwoTone": false,
      "MinusSquareFilled": false,
      "RobotOutlined": false,
      "CoffeeOutlined": false,
      "PauseCircleTwoTone": false,
      "FilePdfTwoTone": false,
      "TwitterOutlined": false,
      "ExperimentOutlined": false,
      "TruckFilled": false,
      "WeiboCircleOutlined": false,
      "AccountBookTwoTone": false,
      "DollarOutlined": true,
      "HighlightOutlined": false,
      "PullRequestOutlined": false,
      "BorderlessTableOutlined": false,
      "VerticalAlignTopOutlined": false,
      "AmazonSquareFilled": false,
      "FrownOutlined": false,
      "ContactsTwoTone": false,
      "GooglePlusSquareFilled": false,
      "RadiusUprightOutlined": false,
      "UnderlineOutlined": false,
      "AlibabaOutlined": false,
      "BellFilled": false,
      "FilterTwoTone": false,
      "BuildFilled": false,
      "LayoutFilled": false,
      "ProfileFilled": false,
      "TwitchFilled": false,
      "getTwoToneColor": false,
      "BugTwoTone": false,
      "MedicineBoxFilled": false,
      "FileWordTwoTone": false,
      "CarTwoTone": false,
      "PropertySafetyOutlined": false,
      "ReadFilled": false,
      "SecurityScanOutlined": false,
      "SearchOutlined": false,
      "LeftCircleFilled": false,
      "CustomerServiceTwoTone": false,
      "FileMarkdownTwoTone": false,
      "ExportOutlined": false,
      "ArrowLeftOutlined": false,
      "CreditCardOutlined": false,
      "EllipsisOutlined": false,
      "BehanceSquareFilled": false,
      "WalletOutlined": false,
      "AlertFilled": false,
      "PlaySquareFilled": false,
      "CheckCircleOutlined": false,
      "CopyTwoTone": false,
      "EuroCircleOutlined": false,
      "AlignRightOutlined": false,
      "ZhihuCircleFilled": false,
      "UserAddOutlined": false,
      "SwitcherOutlined": false,
      "BilibiliOutlined": false,
      "CloseCircleFilled": false,
      "CodeSandboxCircleFilled": false,
      "GiftFilled": false,
      "LineChartOutlined": false,
      "CiOutlined": false,
      "QqSquareFilled": false,
      "PhoneTwoTone": false,
      "StopOutlined": false,
      "RestOutlined": false,
      "SlidersOutlined": false,
      "VideoCameraFilled": false,
      "HighlightTwoTone": false,
      "FilePdfFilled": false,
      "FundProjectionScreenOutlined": false,
      "ConsoleSqlOutlined": false,
      "ApiFilled": false,
      "DeleteRowOutlined": false,
      "DribbbleSquareFilled": false,
      "FileAddTwoTone": false,
      "IeCircleFilled": false,
      "NotificationFilled": false,
      "RightSquareFilled": false,
      "BuildTwoTone": false,
      "GitlabOutlined": false,
      "LaptopOutlined": false,
      "PlayCircleOutlined": false,
      "SwitcherFilled": false,
      "CreditCardTwoTone": false,
      "VerticalAlignMiddleOutlined": false,
      "DeleteOutlined": true,
      "WarningFilled": false,
      "RightCircleTwoTone": false,
      "MoneyCollectTwoTone": false,
      "StopFilled": false,
      "InstagramFilled": false,
      "PoundCircleFilled": false,
      "EyeInvisibleFilled": false,
      "Html5TwoTone": false,
      "StrikethroughOutlined": false,
      "TaobaoOutlined": false,
      "createFromIconfontCN": false,
      "ApartmentOutlined": false,
      "DislikeTwoTone": false,
      "StepBackwardOutlined": false,
      "CaretLeftFilled": false,
      "InfoCircleFilled": false,
      "MergeFilled": false,
      "VerticalRightOutlined": false,
      "LinkedinOutlined": false,
      "UpCircleTwoTone": false,
      "UpSquareOutlined": false,
      "CheckSquareOutlined": false,
      "StarFilled": false,
      "CarFilled": false,
      "BoxPlotTwoTone": false,
      "RedoOutlined": false,
      "TagOutlined": false,
      "FileAddOutlined": false,
      "HolderOutlined": false,
      "KeyOutlined": false,
      "PlusCircleTwoTone": false,
      "MinusCircleFilled": false,
      "GoogleOutlined": false,
      "PieChartFilled": false,
      "InsertRowBelowOutlined": false,
      "YoutubeFilled": false,
      "AlipaySquareFilled": false,
      "RestFilled": false,
      "TabletOutlined": false,
      "AccountBookOutlined": false,
      "DollarTwoTone": false,
      "InboxOutlined": false,
      "LockFilled": false,
      "ExpandOutlined": false,
      "PrinterTwoTone": false,
      "RobotFilled": false,
      "SlidersFilled": false,
      "DownOutlined": false,
      "FileUnknownTwoTone": false,
      "TabletFilled": false,
      "VideoCameraOutlined": false,
      "FileMarkdownFilled": false,
      "SmallDashOutlined": false,
      "ArrowUpOutlined": true,
      "OpenAIFilled": false,
      "PictureFilled": false,
      "CameraOutlined": false,
      "IdcardFilled": false,
      "TwitterSquareFilled": false,
      "CaretRightOutlined": false,
      "DownSquareOutlined": false,
      "ClearOutlined": false,
      "BorderInnerOutlined": false,
      "CiCircleFilled": false,
      "BoxPlotOutlined": false,
      "IdcardOutlined": false,
      "ImportOutlined": false,
      "BulbTwoTone": false,
      "FileFilled": false,
      "WeiboSquareFilled": false,
      "AliwangwangOutlined": false,
      "HeartTwoTone": false,
      "PayCircleOutlined": false,
      "RightOutlined": false,
      "MoonOutlined": false,
      "AuditOutlined": false,
      "ScanOutlined": false,
      "SmileFilled": false,
      "RedditCircleFilled": false,
      "MailFilled": false,
      "BorderBottomOutlined": false,
      "FormOutlined": true,
      "YuqueOutlined": false,
      "DashboardTwoTone": false,
      "PushpinOutlined": false,
      "ProductFilled": false,
      "YoutubeOutlined": false,
      "MenuOutlined": false,
      "CarryOutFilled": false,
      "GithubFilled": false,
      "FontColorsOutlined": false,
      "BarChartOutlined": true,
      "GithubOutlined": false,
      "MinusCircleTwoTone": false,
      "AlertTwoTone": false,
      "LeftSquareOutlined": false,
      "RadarChartOutlined": false,
      "SlackCircleFilled": false,
      "BoxPlotFilled": false,
      "BookTwoTone": false,
      "FlagOutlined": false,
      "MailTwoTone": false,
      "CalculatorTwoTone": false,
      "MehTwoTone": false,
      "VerticalAlignBottomOutlined": false,
      "RadiusBottomrightOutlined": false,
      "CodeTwoTone": false,
      "VideoCameraTwoTone": false,
      "BaiduOutlined": false,
      "ExclamationCircleOutlined": false,
      "FullscreenExitOutlined": false,
      "InfoOutlined": false,
      "PoundCircleOutlined": false,
      "FileImageOutlined": false,
      "AntDesignOutlined": false,
      "BarsOutlined": false,
      "CodepenCircleOutlined": false,
      "DatabaseOutlined": false,
      "LinuxOutlined": false,
      "SnippetsTwoTone": false,
      "BellTwoTone": false,
      "EuroCircleTwoTone": false,
      "CarOutlined": false,
      "TrademarkCircleOutlined": false,
      "TranslationOutlined": false,
      "UsergroupAddOutlined": false,
      "CalendarOutlined": false,
      "BorderOuterOutlined": false,
      "CloudOutlined": false,
      "DropboxOutlined": false,
      "ExceptionOutlined": false,
      "SettingFilled": false,
      "StepBackwardFilled": false,
      "CloudTwoTone": false,
      "OneToOneOutlined": false,
      "WechatWorkOutlined": false,
      "ZhihuSquareFilled": false,
      "UsbFilled": false,
      "AppstoreOutlined": true,
      "MoonFilled": false,
      "ProductOutlined": false,
      "PlusCircleOutlined": false,
      "PlaySquareOutlined": false,
      "FallOutlined": false,
      "ReconciliationTwoTone": false,
      "CopyOutlined": false,
      "AntCloudOutlined": false,
      "GiftTwoTone": false,
      "GoldTwoTone": false,
      "MinusSquareOutlined": false,
      "DashboardOutlined": true,
      "FolderOpenTwoTone": false,
      "SunFilled": false,
      "ShopFilled": false,
      "ShoppingOutlined": false,
      "DashOutlined": false,
      "MedicineBoxOutlined": false,
      "CommentOutlined": false,
      "MailOutlined": false,
      "TikTokFilled": false,
      "XOutlined": false,
      "BulbOutlined": false,
      "FileOutlined": false,
      "EnvironmentOutlined": false,
      "FunctionOutlined": false,
      "CheckSquareFilled": false,
      "ContactsFilled": false,
      "LineOutlined": false,
      "CarryOutOutlined": false,
      "RotateRightOutlined": false,
      "DragOutlined": false,
      "SwitcherTwoTone": false,
      "AlipayOutlined": false,
      "BorderOutlined": false,
      "DropboxSquareFilled": false,
      "LikeTwoTone": false,
      "MoreOutlined": false,
      "MutedFilled": false,
      "FolderOutlined": false,
      "PicCenterOutlined": false,
      "ToolTwoTone": false,
      "CaretDownOutlined": false,
      "HomeFilled": false,
      "CodeFilled": false,
      "ProfileTwoTone": false,
      "UserSwitchOutlined": false,
      "FundFilled": false,
      "WalletFilled": false,
      "BlockOutlined": false,
      "CrownOutlined": false,
      "FileTextOutlined": false,
      "FileUnknownOutlined": false,
      "SortDescendingOutlined": false,
      "TwitterCircleFilled": false,
      "PlaySquareTwoTone": false,
      "HistoryOutlined": false,
      "GoogleSquareFilled": false,
      "EuroOutlined": false,
      "ContainerFilled": false,
      "FileDoneOutlined": false,
      "HighlightFilled": false,
      "InfoCircleOutlined": false,
      "AlipayCircleFilled": false,
      "BehanceOutlined": false,
      "PercentageOutlined": false,
      "PythonOutlined": false,
      "SafetyOutlined": false,
      "ControlFilled": false,
      "ScheduleOutlined": false,
      "PlusSquareOutlined": false,
      "BorderVerticleOutlined": false,
      "AudioTwoTone": false,
      "SketchSquareFilled": false,
      "HddTwoTone": false,
      "PoweroffOutlined": false,
      "InsuranceOutlined": false,
      "Loading3QuartersOutlined": false,
      "HomeOutlined": false,
      "CloudFilled": false,
      "CloudServerOutlined": false,
      "DribbbleOutlined": false,
      "FullscreenOutlined": false,
      "NodeIndexOutlined": false,
      "RightSquareOutlined": false,
      "SplitCellsOutlined": false,
      "StockOutlined": false,
      "QuestionOutlined": false,
      "SecurityScanFilled": false,
      "TagFilled": false,
      "CheckCircleTwoTone": false,
      "PauseCircleOutlined": false,
      "SpotifyOutlined": false,
      "UpOutlined": false,
      "CloseSquareOutlined": false,
      "NodeExpandOutlined": false,
      "KubernetesOutlined": false,
      "PoundOutlined": false,
      "WeiboCircleFilled": false,
      "BellOutlined": true,
      "FieldStringOutlined": false,
      "SafetyCertificateTwoTone": false,
      "GoldenFilled": false,
      "WomanOutlined": false,
      "BugFilled": false,
      "BookOutlined": false,
      "DiffTwoTone": false,
      "LayoutTwoTone": false,
      "CloudDownloadOutlined": false,
      "AppstoreAddOutlined": false,
      "CaretLeftOutlined": false,
      "DatabaseTwoTone": false,
      "CloseCircleTwoTone": false,
      "CloseSquareTwoTone": false,
      "ArrowsAltOutlined": false,
      "FundOutlined": false,
      "FunnelPlotTwoTone": false,
      "Html5Outlined": false,
      "PlusOutlined": false,
      "CalculatorFilled": false,
      "CiCircleOutlined": false,
      "FundViewOutlined": false,
      "TaobaoCircleFilled": false,
      "WeiboOutlined": false,
      "WindowsFilled": false,
      "MediumSquareFilled": false,
      "SubnodeOutlined": false,
      "UsergroupDeleteOutlined": false,
      "FieldTimeOutlined": false,
      "SlidersTwoTone": false,
      "BehanceCircleFilled": false,
      "EyeTwoTone": false,
      "SisternodeOutlined": false,
      "CaretDownFilled": false,
      "ArrowRightOutlined": false,
      "FundTwoTone": false,
      "TagsOutlined": false,
      "MergeCellsOutlined": false,
      "DownCircleOutlined": false,
      "ExclamationCircleTwoTone": false,
      "EyeInvisibleOutlined": false,
      "VerticalLeftOutlined": false,
      "AndroidOutlined": false,
      "DownSquareTwoTone": false,
      "FunnelPlotOutlined": false,
      "MedicineBoxTwoTone": false,
      "ShoppingTwoTone": false,
      "BookFilled": false,
      "JavaScriptOutlined": false,
      "ToolOutlined": false,
      "PinterestOutlined": false,
      "UsbTwoTone": false,
      "OpenAIOutlined": false,
      "FireTwoTone": false,
      "ProjectFilled": false,
      "EyeOutlined": false,
      "RedEnvelopeFilled": false,
      "WechatOutlined": false,
      "ExpandAltOutlined": false,
      "FireFilled": false,
      "InstagramOutlined": false,
      "ProjectTwoTone": false,
      "RedEnvelopeOutlined": false,
      "SyncOutlined": false,
      "TikTokOutlined": false,
      "EditTwoTone": false,
      "BranchesOutlined": false,
      "ShoppingFilled": false,
      "ShareAltOutlined": false,
      "chunk_characteristics": {
        "entry_module_id": "../../../node_modules/.pnpm/@ant-design+icons@5.6.1_react-dom@18.3.1_react@18.3.1/node_modules/@ant-design/icons/es/index.js",
        "is_runtime_chunk": false,
        "has_runtime": false,
        "is_entrypoint": false,
        "can_be_initial": false,
        "is_only_initial": false,
        "chunk_format": "jsonp",
        "chunk_loading_type": null,
        "runtime_names": [
          "main"
        ],
        "entry_name": null,
        "has_async_chunks": false,
        "chunk_files": [
          "node_modules_pnpm_ant-design_icons_5_6_1_react-dom_18_3_1_react_18_3_1_node_modules_ant-desig-f1ca590.js"
        ],
        "is_shared_chunk": false,
        "shared_modules": []
      }
    },
    "dayjs": {
      "chunk_characteristics": {
        "entry_module_id": "../../../node_modules/.pnpm/dayjs@1.11.13/node_modules/dayjs/dayjs.min.js",
        "is_runtime_chunk": false,
        "has_runtime": false,
        "is_entrypoint": false,
        "can_be_initial": false,
        "is_only_initial": false,
        "chunk_format": "jsonp",
        "chunk_loading_type": null,
        "runtime_names": [
          "main"
        ],
        "entry_name": null,
        "has_async_chunks": false,
        "chunk_files": [
          "node_modules_pnpm_dayjs_1_11_13_node_modules_dayjs_dayjs_min_js.js"
        ],
        "is_shared_chunk": false,
        "shared_modules": []
      }
    },
    "chart.js": {
      "PieController": true,
      "DoughnutController": true,
      "BarController": true,
      "elements": false,
      "Animation": false,
      "RadarController": true,
      "Animations": false,
      "CategoryScale": true,
      "LineController": true,
      "controllers": false,
      "SubTitle": false,
      "BubbleController": true,
      "Interaction": false,
      "animator": false,
      "PolarAreaController": true,
      "Legend": true,
      "BasicPlatform": false,
      "_adapters": false,
      "LinearScale": true,
      "layouts": false,
      "DatasetController": false,
      "DomPlatform": false,
      "plugins": false,
      "Scale": false,
      "Colors": false,
      "defaults": false,
      "TimeScale": false,
      "registerables": false,
      "ArcElement": true,
      "ScatterController": true,
      "Decimation": false,
      "Filler": false,
      "PointElement": true,
      "LineElement": true,
      "RadialLinearScale": false,
      "BasePlatform": false,
      "LogarithmicScale": false,
      "Ticks": false,
      "Tooltip": true,
      "BarElement": false,
      "Element": false,
      "Chart": true,
      "Title": true,
      "_detectPlatform": false,
      "TimeSeriesScale": false,
      "registry": false,
      "scales": false,
      "chunk_characteristics": {
        "entry_module_id": "../../../node_modules/.pnpm/chart.js@4.5.0/node_modules/chart.js/dist/chart.js",
        "is_runtime_chunk": false,
        "has_runtime": false,
        "is_entrypoint": false,
        "can_be_initial": false,
        "is_only_initial": false,
        "chunk_format": "jsonp",
        "chunk_loading_type": null,
        "runtime_names": [
          "main"
        ],
        "entry_name": null,
        "has_async_chunks": false,
        "chunk_files": [
          "node_modules_pnpm_chart_js_4_5_0_node_modules_chart_js_dist_chart_js.js"
        ],
        "is_shared_chunk": false,
        "shared_modules": []
      }
    },
    "antd": {
      "Table": true,
      "Modal": false,
      "Popover": false,
      "DatePicker": false,
      "InputNumber": false,
      "FloatButton": false,
      "Space": true,
      "Row": true,
      "Tooltip": false,
      "Empty": false,
      "Grid": false,
      "Tour": false,
      "BackTop": false,
      "Descriptions": false,
      "QRCode": false,
      "ColorPicker": false,
      "Slider": false,
      "List": false,
      "notification": false,
      "Pagination": false,
      "Typography": true,
      "Card": true,
      "Segmented": false,
      "TimePicker": false,
      "message": false,
      "AutoComplete": false,
      "Upload": false,
      "Tabs": true,
      "Breadcrumb": false,
      "Badge": true,
      "Spin": true,
      "Splitter": false,
      "Collapse": false,
      "Dropdown": true,
      "Divider": true,
      "Statistic": true,
      "Result": false,
      "Button": true,
      "Calendar": false,
      "Timeline": false,
      "Menu": true,
      "Image": false,
      "Radio": false,
      "Mentions": false,
      "Affix": false,
      "Drawer": false,
      "Tag": true,
      "Watermark": false,
      "Form": true,
      "Input": true,
      "Avatar": true,
      "Layout": true,
      "version": false,
      "ConfigProvider": true,
      "Rate": false,
      "Steps": false,
      "Alert": true,
      "Transfer": false,
      "Tree": false,
      "Cascader": false,
      "Popconfirm": false,
      "Select": true,
      "Anchor": false,
      "Switch": true,
      "Col": true,
      "Carousel": false,
      "Progress": false,
      "Skeleton": false,
      "App": false,
      "theme": false,
      "Flex": false,
      "Checkbox": false,
      "TreeSelect": false,
      "unstableSetRender": false,
      "chunk_characteristics": {
        "entry_module_id": "../../../node_modules/.pnpm/antd@5.27.0_react-dom@18.3.1_react@18.3.1/node_modules/antd/es/index.js",
        "is_runtime_chunk": false,
        "has_runtime": false,
        "is_entrypoint": false,
        "can_be_initial": false,
        "is_only_initial": false,
        "chunk_format": "jsonp",
        "chunk_loading_type": null,
        "runtime_names": [
          "main"
        ],
        "entry_name": null,
        "has_async_chunks": true,
        "chunk_files": [
          "node_modules_pnpm_antd_5_27_0_react-dom_18_3_1_react_18_3_1_node_modules_antd_es_index_js-_140c0.js"
        ],
        "is_shared_chunk": true,
        "shared_modules": [
          "@ant-design/icons",
          "dayjs",
          "react-dom",
          "react"
        ]
      }
    },
    "react-dom": {
      "flushSync": true,
      "unmountComponentAtNode": false,
      "hydrate": false,
      "unstable_batchedUpdates": true,
      "findDOMNode": false,
      "createRoot": false,
      "hydrateRoot": false,
      "__SECRET_INTERNALS_DO_NOT_USE_OR_YOU_WILL_BE_FIRED": false,
      "unstable_renderSubtreeIntoContainer": false,
      "render": false,
      "createPortal": true,
      "version": false,
      "chunk_characteristics": {
        "entry_module_id": "../../../node_modules/.pnpm/react-dom@18.3.1_react@18.3.1/node_modules/react-dom/index.js",
        "is_runtime_chunk": false,
        "has_runtime": false,
        "is_entrypoint": false,
        "can_be_initial": false,
        "is_only_initial": false,
        "chunk_format": "jsonp",
        "chunk_loading_type": null,
        "runtime_names": [
          "main"
        ],
        "entry_name": null,
        "has_async_chunks": true,
        "chunk_files": [
          "node_modules_pnpm_react-dom_18_3_1_react_18_3_1_node_modules_react-dom_index_js-_47d21.js"
        ],
        "is_shared_chunk": true,
        "shared_modules": [
          "react"
        ]
      }
    },
    "react-redux": {
      "createSelectorHook": false,
      "useStore": false,
      "batch": false,
      "Provider": true,
      "createDispatchHook": false,
      "connect": false,
      "shallowEqual": false,
      "ReactReduxContext": false,
      "useDispatch": true,
      "createStoreHook": false,
      "useSelector": true,
      "chunk_characteristics": {
        "entry_module_id": "../../../node_modules/.pnpm/react-redux@9.2.0_@types+react@18.3.23_react@18.3.1_redux@5.0.1/node_modules/react-redux/dist/react-redux.mjs",
        "is_runtime_chunk": false,
        "has_runtime": false,
        "is_entrypoint": false,
        "can_be_initial": false,
        "is_only_initial": false,
        "chunk_format": "jsonp",
        "chunk_loading_type": null,
        "runtime_names": [
          "main"
        ],
        "entry_name": null,
        "has_async_chunks": true,
        "chunk_files": [
          "node_modules_pnpm_react-redux_9_2_0__types_react_18_3_23_react_18_3_1_redux_5_0_1_node_module-c6d9df1.js"
        ],
        "is_shared_chunk": true,
        "shared_modules": [
          "react"
        ]
      }
    }
  }
}